LICENSE
LICENSE.txt
README.md
setup.cfg
setup.py
tcell_agent/__init__.py
tcell_agent/agent.py
tcell_agent/global_state.py
tcell_agent/system_info.py
tcell_agent/tcell_logger.py
tcell_agent/version.py
tcell_agent.egg-info/PKG-INFO
tcell_agent.egg-info/SOURCES.txt
tcell_agent.egg-info/dependency_links.txt
tcell_agent.egg-info/requires.txt
tcell_agent.egg-info/top_level.txt
tcell_agent/appsensor/__init__.py
tcell_agent/appsensor/meta.py
tcell_agent/bin/tcell_agent
tcell_agent/config/__init__.py
tcell_agent/config/configuration.py
tcell_agent/converters/__init__.py
tcell_agent/converters/params.py
tcell_agent/events/__init__.py
tcell_agent/events/app_config_settings.py
tcell_agent/events/app_route.py
tcell_agent/events/base_event.py
tcell_agent/events/discovery.py
tcell_agent/events/dlp.py
tcell_agent/events/server_agent_packages.py
tcell_agent/events/settings_event.py
tcell_agent/events/startup_events.py
tcell_agent/features/__init__.py
tcell_agent/features/headers.py
tcell_agent/features/request_timing.py
tcell_agent/instrumentation/__init__.py
tcell_agent/instrumentation/better_ip_address.py
tcell_agent/instrumentation/cmdi.py
tcell_agent/instrumentation/context.py
tcell_agent/instrumentation/decorators.py
tcell_agent/instrumentation/headers_cleaner.py
tcell_agent/instrumentation/manager.py
tcell_agent/instrumentation/startup.py
tcell_agent/instrumentation/utils.py
tcell_agent/instrumentation/djangoinst/__init__.py
tcell_agent/instrumentation/djangoinst/app.py
tcell_agent/instrumentation/djangoinst/appfirewall.py
tcell_agent/instrumentation/djangoinst/blocking.py
tcell_agent/instrumentation/djangoinst/check_agent_startup.py
tcell_agent/instrumentation/djangoinst/compatability.py
tcell_agent/instrumentation/djangoinst/config.py
tcell_agent/instrumentation/djangoinst/contrib_auth.py
tcell_agent/instrumentation/djangoinst/database_error_wrapper.py
tcell_agent/instrumentation/djangoinst/dlp.py
tcell_agent/instrumentation/djangoinst/headers.py
tcell_agent/instrumentation/djangoinst/meta.py
tcell_agent/instrumentation/djangoinst/middleware_access.py
tcell_agent/instrumentation/djangoinst/models.py
