Metadata-Version: 2.1
Name: tcell-agent
Version: 1.10.0
Summary: tCell Python Agent
Home-page: https://www.rapid7.com/products/tcell/
Author: Rapid7
License: Free-to-use, proprietary software.
Platform: UNKNOWN
License-File: LICENSE
License-File: LICENSE.txt
